README.md
setup.py
src/sentry_dingding/__init__.py
src/sentry_dingding/forms.py
src/sentry_dingding/plugin.py
src/sentry_dingtalk_robot.egg-info/PKG-INFO
src/sentry_dingtalk_robot.egg-info/SOURCES.txt
src/sentry_dingtalk_robot.egg-info/dependency_links.txt
src/sentry_dingtalk_robot.egg-info/entry_points.txt
src/sentry_dingtalk_robot.egg-info/requires.txt
src/sentry_dingtalk_robot.egg-info/top_level.txt