Metadata-Version: 2.1
Name: sentry-dingtalk-robot
Version: 0.0.2
Summary: A Sentry extension which integrates with Dinttalk robot.
Home-page: https://github.com/loopbless/sentry-dingding
Author: loopbless
Author-email: 243917133@qq.com
License: MIT
Keywords: sentry dingding dingtalk
Platform: UNKNOWN
Classifier: Programming Language :: Python :: 2.7
Classifier: License :: OSI Approved :: MIT License
